{"__type__":"cc.JsonAsset","_name":"round8_jinbi","json":[{"id":0,"x":60.81,"y":-154.4,"enemy":[],"Obstruction":[],"chest":[],"dou":0,"creatnumber":0,"vertical":0,"coin":[{"x":-100,"y":111.5},{"x":-60,"y":111.5},{"x":-20,"y":111.5},{"x":20,"y":111.5},{"x":60,"y":111.5},{"x":100,"y":111.5},{"x":-100,"y":151.5},{"x":-60,"y":151.5},{"x":-20,"y":151.5},{"x":20,"y":151.5},{"x":60,"y":151.5},{"x":100,"y":151.5}]},{"id":4,"x":490.38,"y":-183.04,"enemy":[],"Obstruction":[{"id":2,"pos":{"x":-4.98,"y":127}}],"chest":[],"dou":0,"creatnumber":0,"vertical":0,"coin":[{"x":-141.3497306337664,"y":221.63424124513614},{"x":-182.4392247971906,"y":220.38910505836571},{"x":-20,"y":142.5},{"x":20,"y":142.5},{"x":181.14054173977445,"y":219.1439688715953},{"x":140.05104757635036,"y":220.38910505836571},{"x":-141.3497306337664,"y":261.4785992217899},{"x":-182.4392247971906,"y":262.72373540856034},{"x":-20,"y":182.5},{"x":20,"y":182.5},{"x":181.14054173977445,"y":261.4785992217899},{"x":140.05104757635036,"y":261.4785992217899},{"x":-100,"y":222.5},{"x":-60,"y":222.5},{"x":-20,"y":222.5},{"x":20,"y":222.5},{"x":60,"y":222.5},{"x":100,"y":222.5},{"x":-100,"y":262.5},{"x":-60,"y":262.5},{"x":-20,"y":262.5},{"x":20,"y":262.5},{"x":60,"y":262.5},{"x":100,"y":262.5}]},{"id":3,"x":862.03,"y":-171.83,"enemy":[],"Obstruction":[],"chest":[],"dou":0,"creatnumber":0,"vertical":0,"coin":[{"x":-100,"y":211.5},{"x":-60,"y":211.5},{"x":-20,"y":211.5},{"x":20,"y":211.5},{"x":60,"y":211.5},{"x":100,"y":211.5},{"x":-100,"y":251.5},{"x":-60,"y":251.5},{"x":-20,"y":251.5},{"x":20,"y":251.5},{"x":60,"y":251.5},{"x":100,"y":251.5}]}]}